{"cod_insee": "59234", "cod_dpt": "59", "commune": "Flers-en-Escrebieux", "commune_norm": "flers en escrebieux", "population_2023": 5424, "inscrits": 3745, "participation_t1": 57.65, "nb_listes": 2, "statut": "elu_t1", "listes": [{"num_panneau": 1, "nom_liste": "AGIR ENSEMBLE", "tete_liste": "Jean-Jacques PEYRAUD", "nuance_code": "LDVD", "nuance_lib": "Liste divers droite", "couleur": "#B0B0B0", "voix_t1": 1362, "score_t1": 64.98, "sieges": 24, "elu": true}, {"num_panneau": 2, "nom_liste": "POUR UN RENOUVEAU FLERSOIS", "tete_liste": "Olivier MICHEL", "nuance_code": "LDVD", "nuance_lib": "Liste divers droite", "couleur": "#B0B0B0", "voix_t1": 734, "score_t1": 35.02, "sieges": 5, "elu": true}]}