{"cod_insee": "59269", "cod_dpt": "59", "commune": "Gouzeaucourt", "commune_norm": "gouzeaucourt", "population_2023": 1413, "inscrits": 1173, "participation_t1": 47.4, "nb_listes": 1, "statut": "elu_t1", "futur_maire": "Jacques RICHARD", "listes": [{"num_panneau": 1, "nom_liste": "ENSEMBLE POUR UN TERRITOIRE VIVANT", "tete_liste": "Jacques RICHARD", "nuance_code": "", "nuance_lib": "", "couleur": "#B0B0B0", "voix_t1": 440, "score_t1": 100.0, "sieges": 15, "elu": true, "candidats": ["Jacques RICHARD", "Céline LAVALLÉE", "Yannick CAREMELLE", "Delphine LEFEBVRE", "Hervé DECAMPS", "Marie-Françoise CHOQUET", "Paul DELOBEL", "Delphine REBEILLEAU", "Antoine CAREMELLE", "Julie DUBUS", "David MAUFROY", "Danielle DEFAWE", "Pascal ENGSTER", "Brigitte DELOBEL", "Éric MUNCHOW", "Béatrice LEGRAND", "François MARCHEUX"]}], "listes_t1_rappel": [{"num_panneau": 1, "nom_liste": "ENSEMBLE POUR UN TERRITOIRE VIVANT", "tete_liste": "Jacques RICHARD", "nuance_code": "", "nuance_lib": "", "couleur": "#B0B0B0", "score_t1": 100.0, "voix_t1": 440}]}