{"cod_insee": "59272", "cod_dpt": "59", "commune": "Grand-Fort-Philippe", "commune_norm": "grand fort philippe", "population_2023": 4887, "inscrits": 4111, "participation_t1": 60.74, "nb_listes": 2, "statut": "elu_t1", "listes": [{"num_panneau": 1, "nom_liste": "EPA", "tete_liste": "Romain AGEZ", "nuance_code": "LDVC", "nuance_lib": "Liste divers centre", "couleur": "#B0B0B0", "voix_t1": 1412, "score_t1": 59.01, "sieges": 22, "elu": true}, {"num_panneau": 2, "nom_liste": "avpgd", "tete_liste": "Fabienne DEROY", "nuance_code": "LDVG", "nuance_lib": "Liste divers gauche", "couleur": "#B0B0B0", "voix_t1": 981, "score_t1": 40.99, "sieges": 5, "elu": true}]}