{"cod_insee": "59315", "cod_dpt": "59", "commune": "Houdain-lez-Bavay", "commune_norm": "houdain lez bavay", "population_2023": 902, "inscrits": 669, "participation_t1": 70.7, "nb_listes": 2, "statut": "elu_t1", "listes": [{"num_panneau": 1, "nom_liste": "Un nouvel élan pour Houdain lez Bavay", "tete_liste": "Alain BLAISS", "nuance_code": "", "nuance_lib": "", "couleur": "#B0B0B0", "voix_t1": 156, "score_t1": 34.44, "sieges": null, "elu": true}, {"num_panneau": 2, "nom_liste": "TOUJOURS ENSEMBLE POUR HOUDAIN", "tete_liste": "Nicolas RUTER", "nuance_code": "", "nuance_lib": "", "couleur": "#B0B0B0", "voix_t1": 297, "score_t1": 65.56, "sieges": null, "elu": true}]}