{"cod_insee": "59508", "cod_dpt": "59", "commune": "Roncq", "commune_norm": "roncq", "population_2023": 14075, "inscrits": 11026, "participation_t1": 36.21, "nb_listes": 1, "statut": "elu_t1", "futur_maire": "Rodrigue DESMET", "listes": [{"num_panneau": 1, "nom_liste": "ENSEMBLE POUR RONCQ AVEC RODRIGUE DESMET", "tete_liste": "Rodrigue DESMET", "nuance_code": "LDVD", "nuance_lib": "Liste divers droite", "couleur": "#2e6fa8", "voix_t1": 3330, "score_t1": 100.0, "sieges": 33, "elu": true, "candidats": ["Rodrigue DESMET", "Anne THOREZ", "Romain WAQUET", "Annick CASTELEIN", "Antonio DA SILVA", "Dominique ACKOU", "Thibault TELLIER", "Edwige CARDENIA", "Julien MARIEN", "Rose-Marie BUCHET", "Jean MOTUELLE", "Claudie RIUS", "Franck GILME", "Alexandra COUSTY", "Mustapha GUIROUS", "Virginie LAMBLIN", "Olivier DHONT", "Emilie LEDOUX LIVET", "Xavier DUQUESNE", "Stéphanie PENET", "Michel PETILLON", "Claudine ZAHM", "Hervé HAZEBROUCK", "Caroline LESCOUFFE", "Nathan DJERNI-HAYTE", "Charline BECQUART", "Paul André LEROY", "Lana CHEROUTRE", "Ludovic DELEPIERRE", "Nassima IBAZ", "Alexandre DI BARTOLO", "Virginie LECLUYSE", "Baptiste DECROCK", "Bernadette SANZ", "Thomas BOURGHELLE"]}]}