{"cod_insee": "59557", "cod_dpt": "59", "commune": "Saultain", "commune_norm": "saultain", "population_2023": 2499, "inscrits": 1827, "participation_t1": 69.62, "nb_listes": 2, "statut": "elu_t1", "listes": [{"num_panneau": 1, "nom_liste": "SAULTAIN AVEC VOUS, POUR VOUS", "tete_liste": "Antoine LORENT", "nuance_code": "", "nuance_lib": "", "couleur": "#B0B0B0", "voix_t1": 659, "score_t1": 52.72, "sieges": 15, "elu": true}, {"num_panneau": 2, "nom_liste": "L'avenir ensemble", "tete_liste": "Sandrine DANHIEZ", "nuance_code": "", "nuance_lib": "", "couleur": "#B0B0B0", "voix_t1": 591, "score_t1": 47.28, "sieges": 4, "elu": true}]}