{"cod_insee": "59611", "cod_dpt": "59", "commune": "Verlinghem", "commune_norm": "verlinghem", "population_2023": 2682, "inscrits": 2002, "participation_t1": 55.59, "nb_listes": 1, "statut": "elu_t1", "futur_maire": "Thierry BONTE", "listes": [{"num_panneau": 1, "nom_liste": "VIVEMENT VERLINGHEM", "tete_liste": "Thierry BONTE", "nuance_code": "", "nuance_lib": "", "couleur": "#B0B0B0", "voix_t1": 999, "score_t1": 100.0, "sieges": 23, "elu": true, "candidats": ["Thierry BONTE", "Anne GOFFAUX", "Benoit BOUREL", "Karine ROUSSEAU", "Philippe BUISINE", "Dominique QUINART", "Philippe CAENEN", "Capucine MAYEUR", "Marc DELALLEAU", "Nathalie DE LASSUS SAINT-GENIES", "Eric FORESTIER", "Virginie DELANNOY", "Laurent FRANCOIS", "Christiane MEURILLON", "Thierry DEKOKELAIRE", "Priscilla LE BLAN", "Julien LUTUN", "Hananne SAA", "Nicolas TACHET", "Thaïs HUGBART", "Romain CAILLET", "Annie LESAGE", "Simon LALAU", "Annelore PEREZ", "Nicolas QUINART"]}], "listes_t1_rappel": [{"num_panneau": 1, "nom_liste": "VIVEMENT VERLINGHEM", "tete_liste": "Thierry BONTE", "nuance_code": "", "nuance_lib": "", "couleur": "#B0B0B0", "score_t1": 100.0, "voix_t1": 999}]}