{"cod_insee": "59643", "cod_dpt": "59", "commune": "Warneton", "commune_norm": "warneton", "population_2023": 231, "inscrits": 201, "participation_t1": 55.72, "nb_listes": 1, "statut": "elu_t1", "futur_maire": "Yvon PÉTRONIN", "listes": [{"num_panneau": 1, "nom_liste": "A.P.W Agir pour Warneton", "tete_liste": "Yvon PÉTRONIN", "nuance_code": "", "nuance_lib": "", "couleur": "#B0B0B0", "voix_t1": 103, "score_t1": 100.0, "sieges": null, "elu": true, "candidats": ["Yvon PÉTRONIN", "Claudie DELEDALLE", "Bernard PAREZ", "Véronique LEPOUTRE", "Francis GHESTEM", "Béatrice GOBEYN", "Nicolas DEAN", "Nathalie LAMEYSE", "Benoît MAZURE", "Laury GAUTHIER", "Rémy BEGHIN"]}], "listes_t1_rappel": [{"num_panneau": 1, "nom_liste": "A.P.W Agir pour Warneton", "tete_liste": "Yvon PÉTRONIN", "nuance_code": "", "nuance_lib": "", "couleur": "#B0B0B0", "score_t1": 100.0, "voix_t1": 103}]}