{"cod_insee": "62204", "cod_dpt": "62", "commune": "Campagne-lès-Hesdin", "commune_norm": "campagne les hesdin", "population_2023": 1943, "inscrits": 1225, "participation_t1": 81.47, "nb_listes": 2, "statut": "elu_t1", "listes": [{"num_panneau": 1, "nom_liste": "Ensemble pour bien vivre à Campagne", "tete_liste": "Michel EVRARD", "nuance_code": "", "nuance_lib": "", "couleur": "#B0B0B0", "voix_t1": 636, "score_t1": 67.52, "sieges": 16, "elu": true}, {"num_panneau": 2, "nom_liste": "CAMPAGNE VERS L'AVENIR", "tete_liste": "Eric VERNUSSE", "nuance_code": "", "nuance_lib": "", "couleur": "#B0B0B0", "voix_t1": 306, "score_t1": 32.48, "sieges": 3, "elu": true}]}