{"cod_insee": "62211", "cod_dpt": "62", "commune": "Capelle-Fermont", "commune_norm": "capelle fermont", "population_2023": 223, "inscrits": 174, "participation_t1": 73.56, "nb_listes": 1, "statut": "elu_t1", "futur_maire": "Thomas KOZAK", "listes": [{"num_panneau": 1, "nom_liste": "Préserver notre village, préparer son avenir", "tete_liste": "Thomas KOZAK", "nuance_code": "", "nuance_lib": "", "couleur": "#B0B0B0", "voix_t1": 103, "score_t1": 100.0, "sieges": null, "elu": true, "candidats": ["Thomas KOZAK", "Sabine SURELLE", "Frédéric DHERIN", "Émilie COQUEL", "Maxime STERNADEL", "Élodie D'AMICO", "Sébastien FOULON", "Manon OUSALEM", "Guillaume PINTAPARIS", "Annie DANEL", "Pierre BOUCHEND'HOMME"]}], "listes_t1_rappel": [{"num_panneau": 1, "nom_liste": "Préserver notre village, préparer son avenir", "tete_liste": "Thomas KOZAK", "nuance_code": "", "nuance_lib": "", "couleur": "#B0B0B0", "score_t1": 100.0, "voix_t1": 103}]}