{"cod_insee": "62220", "cod_dpt": "62", "commune": "Cavron-Saint-Martin", "commune_norm": "cavron saint martin", "population_2023": 423, "inscrits": 373, "participation_t1": 80.7, "nb_listes": 2, "statut": "elu_t1", "futur_maire": "Sabine CARON", "listes": [{"num_panneau": 1, "nom_liste": "UNE EQUIPE EN ACTION, TOURNEE VERS DEMAIN", "tete_liste": "Antoine BOLLART", "nuance_code": "", "nuance_lib": "", "couleur": "#B0B0B0", "voix_t1": 115, "score_t1": 39.52, "sieges": null, "elu": false, "candidats": ["Antoine BOLLART", "Marielle ALLOUCHERY", "Guillaume CAPENDU", "Laetitia CARON", "Jean-Pierre CARON", "Stephanie ICIAKENE", "Sebastien SELLIER", "Catherine NIEUVIART", "Cyril RYCKEWAERT", "Caroline FACHAUX", "Anthony DENECQ"]}, {"num_panneau": 2, "nom_liste": "DONNONS DES COULEURS", "tete_liste": "Sabine CARON", "nuance_code": "", "nuance_lib": "", "couleur": "#B0B0B0", "voix_t1": 176, "score_t1": 60.48, "sieges": null, "elu": true, "candidats": ["Sabine CARON", "Dominique EVRARD", "Virginie RIQUET", "Thomas CATTEAU", "Sophie CACHERA", "Henri CARON", "Ludivine DELVINQUIERE", "Cedric COURTINE-CHERUZEL", "Aurelia KAPPES", "Ludovic VASSEUR", "Corinne VANHEDE"]}], "listes_t1_rappel": [{"num_panneau": 1, "nom_liste": "UNE EQUIPE EN ACTION, TOURNEE VERS DEMAIN", "tete_liste": "Antoine BOLLART", "nuance_code": "", "nuance_lib": "", "couleur": "#B0B0B0", "score_t1": 39.52, "voix_t1": 115}, {"num_panneau": 2, "nom_liste": "DONNONS DES COULEURS", "tete_liste": "Sabine CARON", "nuance_code": "", "nuance_lib": "", "couleur": "#B0B0B0", "score_t1": 60.48, "voix_t1": 176}]}