{"cod_insee": "62256", "cod_dpt": "62", "commune": "Crépy", "commune_norm": "crepy", "population_2023": 159, "inscrits": 123, "participation_t1": 80.49, "nb_listes": 1, "statut": "elu_t1", "futur_maire": "Yolande DEBRUYNE", "listes": [{"num_panneau": 1, "nom_liste": "Liste menée par DEBRUYNE Yolande", "tete_liste": "Yolande DEBRUYNE", "nuance_code": "", "nuance_lib": "", "couleur": "#B0B0B0", "voix_t1": 67, "score_t1": 100.0, "sieges": null, "elu": true, "candidats": ["Yolande DEBRUYNE", "Rémi THELLIER", "Séverine DÉZANDRÉ", "Olivier CARREZ", "Claudie DUCROCQ", "François MOREL", "Isabelle RINGARD", "Franck POULAIN", "Michèle LHOMME", "Frédéric HANQUEZ", "Sylvie HANQUEZ"]}]}