{"cod_insee": "62339", "cod_dpt": "62", "commune": "Fleury", "commune_norm": "fleury", "population_2023": 109, "inscrits": 87, "participation_t1": 66.67, "nb_listes": 1, "statut": "elu_t1", "futur_maire": "Jean-Noël VOISEUX", "listes": [{"num_panneau": 1, "nom_liste": "Liste menée par VOISEUX Jean-Noël", "tete_liste": "Jean-Noël VOISEUX", "nuance_code": "", "nuance_lib": "", "couleur": "#B0B0B0", "voix_t1": 54, "score_t1": 100.0, "sieges": null, "elu": true, "candidats": ["Jean-Noël VOISEUX", "Barbara GLORIAN", "Miguel PROYART", "Béatrice PRUVOST", "Renaud BRUNEL", "Thérèse DALONGEVILLE", "Fabien GUILLE", "Aurélia DEMOLIN", "Christian PRUVOST", "Anaïs HUYGHE", "Philippe DELANNOY"]}]}