{"cod_insee": "62388", "cod_dpt": "62", "commune": "Grigny", "commune_norm": "grigny", "population_2023": 290, "inscrits": 214, "participation_t1": 81.31, "nb_listes": 2, "statut": "elu_t1", "futur_maire": "Jean-Luc DUPOND", "listes": [{"num_panneau": 1, "nom_liste": "NOUVELLE LISTE DU CONSEIL SORTANT", "tete_liste": "Jean-Luc DUPOND", "nuance_code": "", "nuance_lib": "", "couleur": "#B0B0B0", "voix_t1": 100, "score_t1": 60.24, "sieges": null, "elu": true, "candidats": ["Jean-Luc DUPOND", "Nathalie PICQUART", "Olivier LANVIN", "Geraldine FIQUET", "Jean-Paul FIQUET", "Chloe DEPRES", "Bernard WHITE", "Ophelie CALON", "Frederic SERGENT", "Cecile STORET", "Loïc DUFRESNES"]}, {"num_panneau": 2, "nom_liste": "Redynamiser notre village", "tete_liste": "Jean-Philippe HAUDIQUET", "nuance_code": "", "nuance_lib": "", "couleur": "#B0B0B0", "voix_t1": 66, "score_t1": 39.76, "sieges": null, "elu": false, "candidats": ["Jean-Philippe HAUDIQUET", "Alexandra CARTON", "Marc DECHEF", "Murielle POUCHAIN", "Serge POTEL", "Jennifer BOCQUILLON", "Christophe SERGENT", "Pauline FRUCHART", "Marcel DELDIQUE", "Charlotte SERGENT"]}], "listes_t1_rappel": [{"num_panneau": 1, "nom_liste": "NOUVELLE LISTE DU CONSEIL SORTANT", "tete_liste": "Jean-Luc DUPOND", "nuance_code": "", "nuance_lib": "", "couleur": "#B0B0B0", "score_t1": 60.24, "voix_t1": 100}, {"num_panneau": 2, "nom_liste": "Redynamiser notre village", "tete_liste": "Jean-Philippe HAUDIQUET", "nuance_code": "", "nuance_lib": "", "couleur": "#B0B0B0", "score_t1": 39.76, "voix_t1": 66}]}