{"cod_insee": "62501", "cod_dpt": "62", "commune": "Lespinoy", "commune_norm": "lespinoy", "population_2023": 243, "inscrits": 190, "participation_t1": 91.05, "nb_listes": 2, "statut": "elu_t1", "listes": [{"num_panneau": 1, "nom_liste": "REUSSIR ENSEMBLE", "tete_liste": "Jeany BACQUET", "nuance_code": "", "nuance_lib": "", "couleur": "#B0B0B0", "voix_t1": 102, "score_t1": 61.45, "sieges": null, "elu": true}, {"num_panneau": 2, "nom_liste": "DU RENOUVEAU POUR LESPINOY", "tete_liste": "Maryse GASTON", "nuance_code": "", "nuance_lib": "", "couleur": "#B0B0B0", "voix_t1": 64, "score_t1": 38.55, "sieges": null, "elu": true}]}