{"cod_insee": "62573", "cod_dpt": "62", "commune": "Meurchin", "commune_norm": "meurchin", "population_2023": 3691, "inscrits": 2957, "participation_t1": 54.45, "nb_listes": 2, "statut": "elu_t1", "futur_maire": "Cathy WASYLIKOW", "listes": [{"num_panneau": 1, "nom_liste": "CONTINUONS ENSEMBLE UNIS POUR MEURCHIN", "tete_liste": "Frédéric ALLOÏ", "nuance_code": "LDVG", "nuance_lib": "Liste divers gauche", "couleur": "#d94b5c", "voix_t1": 486, "score_t1": 32.38, "sieges": 4, "elu": false, "candidats": ["Frédéric ALLOÏ", "Christine HENNACHE", "Ludovic MONTAGNE", "Maryline BAILLET", "Ismaël SCHUBERT", "Dominique BUQUET", "Jean-Louis LEFEBVRE", "Lucile FERET", "Didier DERACHE", "Julie GORNY", "Jérémy REGNIER", "Aurélie LEFEBVRE", "Robert MATTANA", "Véronique MORTELECQUE", "Czeslaw WYCHOWSKI", "Rose-Marie DAVAULT", "Bernard FRUCHART", "Caroline DUBRULLE", "Maxence LEMOINE", "Véronique VIJVERMANS", "Bernard JASPART", "Stéphanie EL BATTAH", "Gilles MARTIN", "Sylviane JASPART", "Frédéric HORCKMANS", "Jeanne Marie VANDAELE WILLOT", "Alain BAILLET", "Brigitte MARTIN", "Laurent MAILLARD"]}, {"num_panneau": 2, "nom_liste": "MEURCHIN, NOTRE AVENIR COMMUN", "tete_liste": "Cathy WASYLIKOW", "nuance_code": "LDVG", "nuance_lib": "Liste divers gauche", "couleur": "#d94b5c", "voix_t1": 1015, "score_t1": 67.62, "sieges": 23, "elu": true, "candidats": ["Cathy WASYLIKOW", "Steve TIRLOIT", "Sandrine MILON-POIGNANT", "Eric RAJCZYK", "Anne DELATTRE", "Guillaume MAYEUR", "Nathalie HAELVOET", "Daniel OUVRY", "Celine SUCKY", "Ludovic PIRC", "Lorelei SION", "Patrice DUPUIS", "Cathy PARSY", "Loic DEPRAETERE", "Martine DUBART", "Noel ROY", "Athenais DRUMETZ", "David MALBRANQUE", "Alexane DELORY", "Guillaume DELPLACE", "Nathalie DEVOS", "Maxime MILON", "Christelle HERENG", "Olivier SOCHARD", "Michele STEFANOU BOURSIER", "Frederic BOSSART", "Sylvie DUPUIS-HIDOT", "Joel LEPREUX"]}]}