{"cod_insee": "62646", "cod_dpt": "62", "commune": "Palluel", "commune_norm": "palluel", "population_2023": 566, "inscrits": 520, "participation_t1": 55.58, "nb_listes": 1, "statut": "elu_t1", "futur_maire": "Thierry GILLERON", "listes": [{"num_panneau": 1, "nom_liste": "DEFENSE DES TRADITIONS ET INTERETS COMMUNAUX", "tete_liste": "Thierry GILLERON", "nuance_code": "", "nuance_lib": "", "couleur": "#B0B0B0", "voix_t1": 252, "score_t1": 100.0, "sieges": null, "elu": true, "candidats": ["Thierry GILLERON", "Martine GARIN", "Gérard DECAUDAIN", "Chantal DELVOYE", "Franck LUCAS", "Marilene LEGAY", "Jérôme ROGEZ", "Véronique SURELLE", "Jean MALOSSI", "Ingrid LEMAIRE", "Nunzio LO CERTO", "Laurence LELORNE", "Romain WARTELLE", "Stéphanie HOLIN", "Thomas PROUVIER"]}], "listes_t1_rappel": [{"num_panneau": 1, "nom_liste": "DEFENSE DES TRADITIONS ET INTERETS COMMUNAUX", "tete_liste": "Thierry GILLERON", "nuance_code": "", "nuance_lib": "", "couleur": "#B0B0B0", "score_t1": 100.0, "voix_t1": 252}]}