{"cod_insee": "62740", "cod_dpt": "62", "commune": "Sains-lès-Pernes", "commune_norm": "sains les pernes", "population_2023": 294, "inscrits": 271, "participation_t1": 78.97, "nb_listes": 2, "statut": "elu_t1", "listes": [{"num_panneau": 1, "nom_liste": "SAINS LES PERNES - VILLAGE DE DEMAIN", "tete_liste": "Doniphane GILBART", "nuance_code": "", "nuance_lib": "", "couleur": "#B0B0B0", "voix_t1": 70, "score_t1": 34.31, "sieges": null, "elu": true}, {"num_panneau": 2, "nom_liste": "ENSEMBLE POUR LES SANCTANOIS", "tete_liste": "Raphaël RAECKELBOOM", "nuance_code": "", "nuance_lib": "", "couleur": "#B0B0B0", "voix_t1": 134, "score_t1": 65.69, "sieges": null, "elu": true}]}